pyjzq/__init__.py
pyjzq/game.py
pyjzq-0.2.dist-info/LICENSE
pyjzq-0.2.dist-info/METADATA
pyjzq-0.2.dist-info/WHEEL
pyjzq-0.2.dist-info/entry_points.txt
pyjzq-0.2.dist-info/top_level.txt
pyjzq-0.2.dist-info/RECORD
