Metadata-Version: 2.1
Name: pyjzq
Version: 0.2
Summary: A command-line tic-tac-toe game
Home-page: https://github.com/tianhukj/pyjzq
Author: tianhukj
Author-email: tianhukj@outlook.com
License: UNKNOWN
Platform: UNKNOWN
Classifier: Programming Language :: Python :: 3
Classifier: License :: OSI Approved :: MIT License
Classifier: Operating System :: OS Independent
Requires-Python: >=3.6
